miasort/__init__.py
miasort/helper.py
miasort/histogram.py
miasort/miasort.py
miasort/plot.py
miasort/records.py
miasort/sort.py
miasort/start.py
miasort-0.1.6.dist-info/LICENSE.txt
miasort-0.1.6.dist-info/METADATA
miasort-0.1.6.dist-info/WHEEL
miasort-0.1.6.dist-info/top_level.txt
miasort-0.1.6.dist-info/RECORD
