Metadata-Version: 2.1
Name: miasort
Version: 0.1.6
Summary: A Tool for Multiplex Chromatin Interaction Analysis by Efficiently Sorting Chromatin Complexes
Home-page: https://github.com/minjikimlab/mia-sort
Author: Zichen Zhang
Author-email: zhangzzc@umich.edu
Classifier: Programming Language :: Python :: 3
Classifier: Operating System :: OS Independent
Requires-Python: >=3.11
License-File: LICENSE.txt
Requires-Dist: matplotlib ==3.9.2
Requires-Dist: pybedtools ==0.10.0
Requires-Dist: setuptools ==70.3.0
